{"version":2,"kind":"Article","sha256":"d5cea2c289ae0eaa9598cfe86c037fb42f458b82824f08db3574a1e54f2cdff7","slug":"index","location":"/README.md","dependencies":[],"frontmatter":{"title":"📘 A Simplified Data Analysis Using an AI Teammate Exploration Cookbook","content_includes_title":false,"open_access":true,"license":{"content":{"id":"CC-BY-4.0","url":"https://creativecommons.org/licenses/by/4.0/","name":"Creative Commons Attribution 4.0 International","free":true,"CC":true},"code":{"id":"Apache-2.0","url":"https://opensource.org/licenses/Apache-2.0","name":"Apache License 2.0","free":true,"osi":true}},"github":"https://github.com/projectpythia/cookbook-template","copyright":"2024","affiliations":[{"id":"UAlbany","name":"University at Albany (SUNY)","department":"Atmospheric and Environmental Sciences","url":"https://www.albany.edu/daes"},{"id":"CISL","name":"NSF National Center for Atmospheric Research","department":"Computational and Information Systems Lab","url":"https://www.cisl.ucar.edu"},{"id":"Unidata","name":"NSF Unidata","url":"https://www.unidata.ucar.edu"},{"id":"Argonne","name":"Argonne National Laboratory","department":"Environmental Science Division","url":"https://www.anl.gov/evs"},{"id":"CarbonPlan","name":"CarbonPlan","url":"https://carbonplan.org"},{"id":"NVIDIA","name":"NVIDIA Corporation","url":"https://www.nvidia.com/"}],"edit_url":"https://github.com/projectpythia/cookbook-template/blob/HEAD/README.md","thumbnail":"/data-science-ai-teammate-cookbook/_preview/28/build/89afeadcbd8a5600c0a40193da3af855.svg","exports":[{"format":"md","filename":"README.md","url":"/data-science-ai-teammate-cookbook/_preview/28/build/README-c3d4a44212b469305b17069081124ab5.md"}]},"mdast":{"type":"root","children":[{"type":"block","children":[{"type":"paragraph","position":{"start":{"line":3,"column":1},"end":{"line":3,"column":1}},"children":[{"type":"text","value":"Tiffany Boyer - Contributor; Dr. Francis Tuluri - Contributor; and Temilouwa - Contributor; Connor Quiroz - Lead","position":{"start":{"line":3,"column":1},"end":{"line":3,"column":1}},"key":"ftBZ5NSOdZ"}],"key":"mL5soygJ1U"},{"type":"thematicBreak","position":{"start":{"line":5,"column":1},"end":{"line":5,"column":1}},"key":"pdNW5mjWGM"},{"type":"heading","depth":2,"position":{"start":{"line":7,"column":1},"end":{"line":7,"column":1}},"children":[{"type":"text","value":"✍️ Authors","position":{"start":{"line":7,"column":1},"end":{"line":7,"column":1}},"key":"MAlgxPsP8K"}],"identifier":"id-authors","label":"✍️ Authors","html_id":"id-authors","implicit":true,"key":"vjvTRADbFa"},{"type":"paragraph","position":{"start":{"line":9,"column":1},"end":{"line":9,"column":1}},"children":[{"type":"text","value":"Authors: ","position":{"start":{"line":9,"column":1},"end":{"line":9,"column":1}},"key":"fbY7a9fBrC"},{"type":"link","url":"https://github.com/IamTemmy","position":{"start":{"line":9,"column":1},"end":{"line":9,"column":1}},"children":[{"type":"text","value":"Temiloluwa Adesola","position":{"start":{"line":9,"column":1},"end":{"line":9,"column":1}},"key":"VGBKax67Y8"}],"urlSource":"https://github.com/IamTemmy","error":true,"key":"lKXMD9KfQQ"},{"type":"text","value":"; ","position":{"start":{"line":9,"column":1},"end":{"line":9,"column":1}},"key":"ZPfPHYJyEv"},{"type":"link","url":"https://github.com/El0quence","position":{"start":{"line":9,"column":1},"end":{"line":9,"column":1}},"children":[{"type":"text","value":"Tiffany Boyer","position":{"start":{"line":9,"column":1},"end":{"line":9,"column":1}},"key":"ClSaGUh080"}],"urlSource":"https://github.com/El0quence","error":true,"key":"WoFeKPqr7f"},{"type":"text","value":"; ","position":{"start":{"line":9,"column":1},"end":{"line":9,"column":1}},"key":"c53p2sChci"},{"type":"link","url":"https://github.com/ftuluiri","position":{"start":{"line":9,"column":1},"end":{"line":9,"column":1}},"children":[{"type":"text","value":"Dr. Francis Tuluri, PhD","position":{"start":{"line":9,"column":1},"end":{"line":9,"column":1}},"key":"UAZ35Q53rA"}],"urlSource":"https://github.com/ftuluiri","error":true,"key":"xCRnzCXrA3"},{"type":"text","value":"; Lead Author, ","position":{"start":{"line":9,"column":1},"end":{"line":9,"column":1}},"key":"GFk5XA3HAy"},{"type":"link","url":"https://github.com/quir1869","position":{"start":{"line":9,"column":1},"end":{"line":9,"column":1}},"children":[{"type":"text","value":"Connor Quiroz","position":{"start":{"line":9,"column":1},"end":{"line":9,"column":1}},"key":"gyBxgI4CBC"}],"urlSource":"https://github.com/quir1869","error":true,"key":"zNCoAnnZIF"}],"key":"SVLJzbbRr4"},{"type":"heading","depth":2,"position":{"start":{"line":11,"column":1},"end":{"line":11,"column":1}},"children":[{"type":"text","value":"Acknowledgements","position":{"start":{"line":11,"column":1},"end":{"line":11,"column":1}},"key":"nz2cN6PflS"}],"identifier":"acknowledgements","label":"Acknowledgements","html_id":"acknowledgements","implicit":true,"key":"NzUNDjpSCi"},{"type":"paragraph","position":{"start":{"line":13,"column":1},"end":{"line":13,"column":1}},"children":[{"type":"text","value":"James Munroe for providing input on project ideation and providing next step guidance for integrating an AI interface in our cookbook.","position":{"start":{"line":13,"column":1},"end":{"line":13,"column":1}},"key":"KTIW3MoyiG"}],"key":"kknmC0ML6a"},{"type":"heading","depth":3,"position":{"start":{"line":15,"column":1},"end":{"line":15,"column":1}},"children":[{"type":"text","value":"🙌 Contributors","position":{"start":{"line":15,"column":1},"end":{"line":15,"column":1}},"key":"qK1uNxf7bn"}],"identifier":"id-contributors","label":"🙌 Contributors","html_id":"id-contributors","implicit":true,"key":"wScOz0zRLv"},{"type":"thematicBreak","position":{"start":{"line":17,"column":1},"end":{"line":17,"column":1}},"key":"Ir2D7gCIlG"},{"type":"link","url":"https://github.com/ProjectPythia/data-science-ai-teammate-cookbook/graphs/contributors","children":[{"type":"image","url":"/data-science-ai-teammate-cookbook/_preview/28/build/89afeadcbd8a5600c0a40193da3af855.svg","key":"erugqjkuRD","urlSource":"https://contrib.rocks/image?repo=ProjectPythia/data-science-ai-teammate-cookbook"},{"type":"text","value":" ","key":"kpr18Vllep"}],"urlSource":"https://github.com/ProjectPythia/data-science-ai-teammate-cookbook/graphs/contributors","error":true,"key":"VXP8REkIRK"},{"type":"image","url":"/data-science-ai-teammate-cookbook/_preview/28/build/thumbnail-8399ae67db84e91a61d441bb3e308128.png","alt":"🐧 Thumbnail","width":300,"key":"mIA01s0ZW3","urlSource":"thumbnails/thumbnail.png"},{"type":"paragraph","position":{"start":{"line":25,"column":1},"end":{"line":27,"column":1}},"children":[{"type":"link","url":"https://github.com/ProjectPythia/cookbook-template/actions/workflows/nightly-build.yaml","position":{"start":{"line":25,"column":1},"end":{"line":25,"column":1}},"children":[{"type":"image","url":"/data-science-ai-teammate-cookbook/_preview/28/build/06605fa84b8680f0497b7822b6283a3e.svg","alt":"🔄 Nightly Build","position":{"start":{"line":25,"column":1},"end":{"line":25,"column":1}},"key":"gymnjHHY0e","urlSource":"https://github.com/ProjectPythia/cookbook-template/actions/workflows/nightly-build.yaml/badge.svg"}],"urlSource":"https://github.com/ProjectPythia/cookbook-template/actions/workflows/nightly-build.yaml","error":true,"key":"nbxWD4Z7Au"},{"type":"text","value":"\n","position":{"start":{"line":25,"column":1},"end":{"line":25,"column":1}},"key":"tUykMSJ3cE"},{"type":"link","url":"https://binder.projectpythia.org/v2/gh/ProjectPythia/cookbook-template/main?labpath=notebooks","position":{"start":{"line":25,"column":1},"end":{"line":25,"column":1}},"children":[{"type":"image","url":"/data-science-ai-teammate-cookbook/_preview/28/build/31e3f387ea168934ca949c27e9927ea4.svg","alt":"🚀 Launch Binder","position":{"start":{"line":25,"column":1},"end":{"line":25,"column":1}},"key":"Rx4LnBsepX","urlSource":"https://binder.projectpythia.org/badge_logo.svg"}],"urlSource":"https://binder.projectpythia.org/v2/gh/ProjectPythia/cookbook-template/main?labpath=notebooks","key":"sBHFmiOYmy"},{"type":"text","value":"\n","position":{"start":{"line":25,"column":1},"end":{"line":25,"column":1}},"key":"UgDmGd34W7"},{"type":"link","url":"https://doi.org/10.5281/zenodo.475509405","position":{"start":{"line":25,"column":1},"end":{"line":25,"column":1}},"children":[{"type":"image","url":"/data-science-ai-teammate-cookbook/_preview/28/build/72a08caa5cbe5f9cce5999dbd1a81dfd.svg","alt":"📌 DOI","position":{"start":{"line":25,"column":1},"end":{"line":25,"column":1}},"key":"i3Da09paHQ","urlSource":"https://zenodo.org/badge/475509405.svg"}],"urlSource":"https://zenodo.org/badge/latestdoi/475509405","data":{"doi":"10.5281/zenodo.475509405"},"internal":false,"protocol":"doi","key":"FihJxebpEN"}],"key":"HK83ANyQWQ"},{"type":"thematicBreak","position":{"start":{"line":29,"column":1},"end":{"line":29,"column":1}},"key":"kQU0sapMGB"}],"key":"qk4PzmBXz1"}],"key":"f6LaFAW1aV"},"references":{"cite":{"order":[],"data":{}}},"footer":{"navigation":{"next":{"title":"How to Cite This Cookbook","url":"/notebooks/how-to-cite","group":"Preamble"}}},"domain":"http://localhost:3000"}